{
  "className": "CData_BattleMode",
  "timestamp": "2025-07-16T14:13:55.466Z",
  "data": {
    "1": {
      "_type": "nested_dictionary",
      "_count": 4,
      "_processed": 4,
      "data": {
        "1": {
          "m_bError": null,
          "m_MainID": "1",
          "m_BattleModeID": "1",
          "m_FirstInherit": "[]",
          "m_BattleGroup": "[]",
          "m_BattleGroupInherit": null,
          "m_CheckErrorRangePercent": "15",
          "m_MonsterType": "[]",
          "m_BPUI": "1",
          "m_AutoBattle": null,
          "m_AutoQuickFormation": "1",
          "m_QuickTeam": "1",
          "m_ReplayLevel": "1",
          "m_ReferOtherTeam": "1",
          "m_FullTeam": "1",
          "m_CheckIfFails": "1"
        },
        "2": {
          "m_bError": null,
          "m_MainID": "1",
          "m_BattleModeID": "2",
          "m_FirstInherit": "[1,1]",
          "m_BattleGroup": "[1,1]",
          "m_BattleGroupInherit": "1",
          "m_CheckErrorRangePercent": "15",
          "m_MonsterType": "[]",
          "m_BPUI": null,
          "m_AutoBattle": null,
          "m_AutoQuickFormation": null,
          "m_QuickTeam": "1",
          "m_ReplayLevel": "1",
          "m_ReferOtherTeam": "1",
          "m_FullTeam": null,
          "m_CheckIfFails": "1"
        },
        "3": {
          "m_bError": null,
          "m_MainID": "1",
          "m_BattleModeID": "3",
          "m_FirstInherit": "[1,1]",
          "m_BattleGroup": "[1,1]",
          "m_BattleGroupInherit": null,
          "m_CheckErrorRangePercent": "15",
          "m_MonsterType": "[]",
          "m_BPUI": "1",
          "m_AutoBattle": null,
          "m_AutoQuickFormation": "1",
          "m_QuickTeam": "1",
          "m_ReplayLevel": "1",
          "m_ReferOtherTeam": "1",
          "m_FullTeam": "1",
          "m_CheckIfFails": "1"
        },
        "4": {
          "m_bError": null,
          "m_MainID": "1",
          "m_BattleModeID": "4",
          "m_FirstInherit": "[1,1]",
          "m_BattleGroup": "[1,1]",
          "m_BattleGroupInherit": null,
          "m_CheckErrorRangePercent": "15",
          "m_MonsterType": "[]",
          "m_BPUI": "1",
          "m_AutoBattle": null,
          "m_AutoQuickFormation": null,
          "m_QuickTeam": "1",
          "m_ReplayLevel": "1",
          "m_ReferOtherTeam": null,
          "m_FullTeam": null,
          "m_CheckIfFails": "1"
        }
      }
    },
    "2": {
      "_type": "nested_dictionary",
      "_count": 7,
      "_processed": 7,
      "data": {
        "1": {
          "m_bError": null,
          "m_MainID": "2",
          "m_BattleModeID": "1",
          "m_FirstInherit": "[1,1]",
          "m_BattleGroup": "[]",
          "m_BattleGroupInherit": null,
          "m_CheckErrorRangePercent": "10",
          "m_MonsterType": "[2]",
          "m_BPUI": null,
          "m_AutoBattle": null,
          "m_AutoQuickFormation": null,
          "m_QuickTeam": "1",
          "m_ReplayLevel": "1",
          "m_ReferOtherTeam": null,
          "m_FullTeam": null,
          "m_CheckIfFails": "1"
        },
        "2": {
          "m_bError": null,
          "m_MainID": "2",
          "m_BattleModeID": "2",
          "m_FirstInherit": "[1,1]",
          "m_BattleGroup": "[]",
          "m_BattleGroupInherit": null,
          "m_CheckErrorRangePercent": "10",
          "m_MonsterType": "[2]",
          "m_BPUI": null,
          "m_AutoBattle": null,
          "m_AutoQuickFormation": null,
          "m_QuickTeam": "1",
          "m_ReplayLevel": "1",
          "m_ReferOtherTeam": null,
          "m_FullTeam": null,
          "m_CheckIfFails": "1"
        },
        "3": {
          "m_bError": null,
          "m_MainID": "2",
          "m_BattleModeID": "3",
          "m_FirstInherit": "[1,1]",
          "m_BattleGroup": "[]",
          "m_BattleGroupInherit": null,
          "m_CheckErrorRangePercent": "10",
          "m_MonsterType": "[2]",
          "m_BPUI": null,
          "m_AutoBattle": null,
          "m_AutoQuickFormation": null,
          "m_QuickTeam": "1",
          "m_ReplayLevel": "1",
          "m_ReferOtherTeam": null,
          "m_FullTeam": null,
          "m_CheckIfFails": "1"
        },
        "4": {
          "m_bError": null,
          "m_MainID": "2",
          "m_BattleModeID": "4",
          "m_FirstInherit": "[1,1]",
          "m_BattleGroup": "[]",
          "m_BattleGroupInherit": null,
          "m_CheckErrorRangePercent": "10",
          "m_MonsterType": "[2]",
          "m_BPUI": null,
          "m_AutoBattle": null,
          "m_AutoQuickFormation": null,
          "m_QuickTeam": "1",
          "m_ReplayLevel": "1",
          "m_ReferOtherTeam": null,
          "m_FullTeam": null,
          "m_CheckIfFails": "1"
        },
        "5": {
          "m_bError": null,
          "m_MainID": "2",
          "m_BattleModeID": "5",
          "m_FirstInherit": "[1,1]",
          "m_BattleGroup": "[]",
          "m_BattleGroupInherit": null,
          "m_CheckErrorRangePercent": "10",
          "m_MonsterType": "[2]",
          "m_BPUI": null,
          "m_AutoBattle": null,
          "m_AutoQuickFormation": null,
          "m_QuickTeam": "1",
          "m_ReplayLevel": "1",
          "m_ReferOtherTeam": null,
          "m_FullTeam": null,
          "m_CheckIfFails": "1"
        },
        "6": {
          "m_bError": null,
          "m_MainID": "2",
          "m_BattleModeID": "6",
          "m_FirstInherit": "[1,1]",
          "m_BattleGroup": "[]",
          "m_BattleGroupInherit": null,
          "m_CheckErrorRangePercent": "10",
          "m_MonsterType": "[2]",
          "m_BPUI": null,
          "m_AutoBattle": null,
          "m_AutoQuickFormation": null,
          "m_QuickTeam": "1",
          "m_ReplayLevel": "1",
          "m_ReferOtherTeam": null,
          "m_FullTeam": null,
          "m_CheckIfFails": "1"
        },
        "7": {
          "m_bError": null,
          "m_MainID": "2",
          "m_BattleModeID": "7",
          "m_FirstInherit": "[1,1]",
          "m_BattleGroup": "[]",
          "m_BattleGroupInherit": null,
          "m_CheckErrorRangePercent": "10",
          "m_MonsterType": "[2]",
          "m_BPUI": null,
          "m_AutoBattle": null,
          "m_AutoQuickFormation": null,
          "m_QuickTeam": "1",
          "m_ReplayLevel": "1",
          "m_ReferOtherTeam": null,
          "m_FullTeam": null,
          "m_CheckIfFails": "1"
        }
      }
    },
    "3": {
      "_type": "nested_dictionary",
      "_count": 5,
      "_processed": 5,
      "data": {
        "1": {
          "m_bError": null,
          "m_MainID": "3",
          "m_BattleModeID": "1",
          "m_FirstInherit": "[1,1]",
          "m_BattleGroup": "[1,1]",
          "m_BattleGroupInherit": null,
          "m_CheckErrorRangePercent": "15",
          "m_MonsterType": "[]",
          "m_BPUI": "1",
          "m_AutoBattle": null,
          "m_AutoQuickFormation": "1",
          "m_QuickTeam": "1",
          "m_ReplayLevel": "1",
          "m_ReferOtherTeam": "1",
          "m_FullTeam": "1",
          "m_CheckIfFails": "1"
        },
        "2": {
          "m_bError": null,
          "m_MainID": "3",
          "m_BattleModeID": "2",
          "m_FirstInherit": "[]",
          "m_BattleGroup": "[]",
          "m_BattleGroupInherit": null,
          "m_CheckErrorRangePercent": "15",
          "m_MonsterType": "[]",
          "m_BPUI": "1",
          "m_AutoBattle": null,
          "m_AutoQuickFormation": "1",
          "m_QuickTeam": "1",
          "m_ReplayLevel": "1",
          "m_ReferOtherTeam": "1",
          "m_FullTeam": "1",
          "m_CheckIfFails": "1"
        },
        "3": {
          "m_bError": null,
          "m_MainID": "3",
          "m_BattleModeID": "3",
          "m_FirstInherit": "[]",
          "m_BattleGroup": "[]",
          "m_BattleGroupInherit": null,
          "m_CheckErrorRangePercent": "15",
          "m_MonsterType": "[]",
          "m_BPUI": "1",
          "m_AutoBattle": null,
          "m_AutoQuickFormation": "1",
          "m_QuickTeam": "1",
          "m_ReplayLevel": "1",
          "m_ReferOtherTeam": "1",
          "m_FullTeam": "1",
          "m_CheckIfFails": "1"
        },
        "4": {
          "m_bError": null,
          "m_MainID": "3",
          "m_BattleModeID": "4",
          "m_FirstInherit": "[]",
          "m_BattleGroup": "[]",
          "m_BattleGroupInherit": null,
          "m_CheckErrorRangePercent": "15",
          "m_MonsterType": "[]",
          "m_BPUI": "1",
          "m_AutoBattle": null,
          "m_AutoQuickFormation": "1",
          "m_QuickTeam": "1",
          "m_ReplayLevel": "1",
          "m_ReferOtherTeam": "1",
          "m_FullTeam": "1",
          "m_CheckIfFails": "1"
        },
        "5": {
          "m_bError": null,
          "m_MainID": "3",
          "m_BattleModeID": "5",
          "m_FirstInherit": "[]",
          "m_BattleGroup": "[]",
          "m_BattleGroupInherit": null,
          "m_CheckErrorRangePercent": "15",
          "m_MonsterType": "[]",
          "m_BPUI": "1",
          "m_AutoBattle": null,
          "m_AutoQuickFormation": "1",
          "m_QuickTeam": "1",
          "m_ReplayLevel": "1",
          "m_ReferOtherTeam": "1",
          "m_FullTeam": "1",
          "m_CheckIfFails": "1"
        }
      }
    },
    "4": {
      "_type": "nested_dictionary",
      "_count": 1,
      "_processed": 1,
      "data": {
        "1": {
          "m_bError": null,
          "m_MainID": "4",
          "m_BattleModeID": "1",
          "m_FirstInherit": "[]",
          "m_BattleGroup": "[]",
          "m_BattleGroupInherit": null,
          "m_CheckErrorRangePercent": "15",
          "m_MonsterType": "[]",
          "m_BPUI": "1",
          "m_AutoBattle": null,
          "m_AutoQuickFormation": null,
          "m_QuickTeam": "1",
          "m_ReplayLevel": null,
          "m_ReferOtherTeam": null,
          "m_FullTeam": null,
          "m_CheckIfFails": "1"
        }
      }
    },
    "5": {
      "_type": "nested_dictionary",
      "_count": 1,
      "_processed": 1,
      "data": {
        "1": {
          "m_bError": null,
          "m_MainID": "5",
          "m_BattleModeID": "1",
          "m_FirstInherit": "[]",
          "m_BattleGroup": "[]",
          "m_BattleGroupInherit": null,
          "m_CheckErrorRangePercent": "15",
          "m_MonsterType": "[]",
          "m_BPUI": "1",
          "m_AutoBattle": null,
          "m_AutoQuickFormation": null,
          "m_QuickTeam": "1",
          "m_ReplayLevel": "1",
          "m_ReferOtherTeam": null,
          "m_FullTeam": null,
          "m_CheckIfFails": "1"
        }
      }
    },
    "6": {
      "_type": "nested_dictionary",
      "_count": 1,
      "_processed": 1,
      "data": {
        "1": {
          "m_bError": null,
          "m_MainID": "6",
          "m_BattleModeID": "1",
          "m_FirstInherit": "[1,1]",
          "m_BattleGroup": "[]",
          "m_BattleGroupInherit": null,
          "m_CheckErrorRangePercent": "15",
          "m_MonsterType": "[]",
          "m_BPUI": "1",
          "m_AutoBattle": null,
          "m_AutoQuickFormation": "1",
          "m_QuickTeam": "1",
          "m_ReplayLevel": null,
          "m_ReferOtherTeam": null,
          "m_FullTeam": "1",
          "m_CheckIfFails": "1"
        }
      }
    },
    "7": {
      "_type": "nested_dictionary",
      "_count": 1,
      "_processed": 1,
      "data": {
        "1": {
          "m_bError": null,
          "m_MainID": "7",
          "m_BattleModeID": "1",
          "m_FirstInherit": "[1,1]",
          "m_BattleGroup": "[1,1]",
          "m_BattleGroupInherit": null,
          "m_CheckErrorRangePercent": "15",
          "m_MonsterType": "[]",
          "m_BPUI": "1",
          "m_AutoBattle": null,
          "m_AutoQuickFormation": null,
          "m_QuickTeam": "1",
          "m_ReplayLevel": null,
          "m_ReferOtherTeam": null,
          "m_FullTeam": null,
          "m_CheckIfFails": "1"
        }
      }
    },
    "8": {
      "_type": "nested_dictionary",
      "_count": 1,
      "_processed": 1,
      "data": {
        "1": {
          "m_bError": null,
          "m_MainID": "8",
          "m_BattleModeID": "1",
          "m_FirstInherit": "[]",
          "m_BattleGroup": "[]",
          "m_BattleGroupInherit": null,
          "m_CheckErrorRangePercent": "10",
          "m_MonsterType": "[2]",
          "m_BPUI": null,
          "m_AutoBattle": null,
          "m_AutoQuickFormation": "1",
          "m_QuickTeam": "1",
          "m_ReplayLevel": null,
          "m_ReferOtherTeam": null,
          "m_FullTeam": null,
          "m_CheckIfFails": "1"
        }
      }
    },
    "9": {
      "_type": "nested_dictionary",
      "_count": 1,
      "_processed": 1,
      "data": {
        "1": {
          "m_bError": null,
          "m_MainID": "9",
          "m_BattleModeID": "1",
          "m_FirstInherit": "[]",
          "m_BattleGroup": "[]",
          "m_BattleGroupInherit": null,
          "m_CheckErrorRangePercent": "10",
          "m_MonsterType": "[2]",
          "m_BPUI": null,
          "m_AutoBattle": null,
          "m_AutoQuickFormation": "1",
          "m_QuickTeam": "1",
          "m_ReplayLevel": null,
          "m_ReferOtherTeam": null,
          "m_FullTeam": null,
          "m_CheckIfFails": "1"
        }
      }
    },
    "10": {
      "_type": "nested_dictionary",
      "_count": 2,
      "_processed": 2,
      "data": {
        "1": {
          "m_bError": null,
          "m_MainID": "10",
          "m_BattleModeID": "1",
          "m_FirstInherit": "[1,1]",
          "m_BattleGroup": "[]",
          "m_BattleGroupInherit": null,
          "m_CheckErrorRangePercent": "15",
          "m_MonsterType": "[]",
          "m_BPUI": "1",
          "m_AutoBattle": null,
          "m_AutoQuickFormation": null,
          "m_QuickTeam": "1",
          "m_ReplayLevel": null,
          "m_ReferOtherTeam": null,
          "m_FullTeam": null,
          "m_CheckIfFails": "1"
        },
        "2": {
          "m_bError": null,
          "m_MainID": "10",
          "m_BattleModeID": "2",
          "m_FirstInherit": "[1,1]",
          "m_BattleGroup": "[]",
          "m_BattleGroupInherit": null,
          "m_CheckErrorRangePercent": "15",
          "m_MonsterType": "[]",
          "m_BPUI": null,
          "m_AutoBattle": null,
          "m_AutoQuickFormation": null,
          "m_QuickTeam": "1",
          "m_ReplayLevel": null,
          "m_ReferOtherTeam": null,
          "m_FullTeam": null,
          "m_CheckIfFails": "1"
        }
      }
    },
    "11": {
      "_type": "nested_dictionary",
      "_count": 1,
      "_processed": 1,
      "data": {
        "1": {
          "m_bError": null,
          "m_MainID": "11",
          "m_BattleModeID": "1",
          "m_FirstInherit": "[1,1]",
          "m_BattleGroup": "[]",
          "m_BattleGroupInherit": null,
          "m_CheckErrorRangePercent": "15",
          "m_MonsterType": "[]",
          "m_BPUI": null,
          "m_AutoBattle": null,
          "m_AutoQuickFormation": "1",
          "m_QuickTeam": null,
          "m_ReplayLevel": null,
          "m_ReferOtherTeam": null,
          "m_FullTeam": null,
          "m_CheckIfFails": "1"
        }
      }
    },
    "12": {
      "_type": "nested_dictionary",
      "_count": 6,
      "_processed": 6,
      "data": {
        "1": {
          "m_bError": null,
          "m_MainID": "12",
          "m_BattleModeID": "1",
          "m_FirstInherit": "[]",
          "m_BattleGroup": "[]",
          "m_BattleGroupInherit": null,
          "m_CheckErrorRangePercent": "15",
          "m_MonsterType": "[]",
          "m_BPUI": "1",
          "m_AutoBattle": null,
          "m_AutoQuickFormation": null,
          "m_QuickTeam": null,
          "m_ReplayLevel": null,
          "m_ReferOtherTeam": null,
          "m_FullTeam": null,
          "m_CheckIfFails": "1"
        },
        "2": {
          "m_bError": null,
          "m_MainID": "12",
          "m_BattleModeID": "2",
          "m_FirstInherit": "[]",
          "m_BattleGroup": "[]",
          "m_BattleGroupInherit": null,
          "m_CheckErrorRangePercent": "15",
          "m_MonsterType": "[]",
          "m_BPUI": "1",
          "m_AutoBattle": null,
          "m_AutoQuickFormation": null,
          "m_QuickTeam": null,
          "m_ReplayLevel": null,
          "m_ReferOtherTeam": null,
          "m_FullTeam": null,
          "m_CheckIfFails": "1"
        },
        "3": {
          "m_bError": null,
          "m_MainID": "12",
          "m_BattleModeID": "3",
          "m_FirstInherit": "[]",
          "m_BattleGroup": "[]",
          "m_BattleGroupInherit": null,
          "m_CheckErrorRangePercent": "15",
          "m_MonsterType": "[]",
          "m_BPUI": "1",
          "m_AutoBattle": null,
          "m_AutoQuickFormation": null,
          "m_QuickTeam": null,
          "m_ReplayLevel": null,
          "m_ReferOtherTeam": null,
          "m_FullTeam": null,
          "m_CheckIfFails": "1"
        },
        "4": {
          "m_bError": null,
          "m_MainID": "12",
          "m_BattleModeID": "4",
          "m_FirstInherit": "[]",
          "m_BattleGroup": "[]",
          "m_BattleGroupInherit": null,
          "m_CheckErrorRangePercent": "15",
          "m_MonsterType": "[]",
          "m_BPUI": null,
          "m_AutoBattle": null,
          "m_AutoQuickFormation": null,
          "m_QuickTeam": null,
          "m_ReplayLevel": null,
          "m_ReferOtherTeam": null,
          "m_FullTeam": null,
          "m_CheckIfFails": "1"
        },
        "5": {
          "m_bError": null,
          "m_MainID": "12",
          "m_BattleModeID": "5",
          "m_FirstInherit": "[]",
          "m_BattleGroup": "[]",
          "m_BattleGroupInherit": null,
          "m_CheckErrorRangePercent": "15",
          "m_MonsterType": "[]",
          "m_BPUI": null,
          "m_AutoBattle": null,
          "m_AutoQuickFormation": null,
          "m_QuickTeam": null,
          "m_ReplayLevel": null,
          "m_ReferOtherTeam": null,
          "m_FullTeam": null,
          "m_CheckIfFails": "1"
        },
        "6": {
          "m_bError": null,
          "m_MainID": "12",
          "m_BattleModeID": "6",
          "m_FirstInherit": "[]",
          "m_BattleGroup": "[]",
          "m_BattleGroupInherit": null,
          "m_CheckErrorRangePercent": "15",
          "m_MonsterType": "[]",
          "m_BPUI": null,
          "m_AutoBattle": null,
          "m_AutoQuickFormation": null,
          "m_QuickTeam": null,
          "m_ReplayLevel": null,
          "m_ReferOtherTeam": null,
          "m_FullTeam": null,
          "m_CheckIfFails": "1"
        }
      }
    },
    "13": {
      "_type": "nested_dictionary",
      "_count": 5,
      "_processed": 5,
      "data": {
        "1": {
          "m_bError": null,
          "m_MainID": "13",
          "m_BattleModeID": "1",
          "m_FirstInherit": "[]",
          "m_BattleGroup": "[]",
          "m_BattleGroupInherit": null,
          "m_CheckErrorRangePercent": "10",
          "m_MonsterType": "[]",
          "m_BPUI": "1",
          "m_AutoBattle": null,
          "m_AutoQuickFormation": null,
          "m_QuickTeam": "1",
          "m_ReplayLevel": null,
          "m_ReferOtherTeam": null,
          "m_FullTeam": null,
          "m_CheckIfFails": "1"
        },
        "2": {
          "m_bError": null,
          "m_MainID": "13",
          "m_BattleModeID": "2",
          "m_FirstInherit": "[]",
          "m_BattleGroup": "[]",
          "m_BattleGroupInherit": null,
          "m_CheckErrorRangePercent": "10",
          "m_MonsterType": "[]",
          "m_BPUI": "1",
          "m_AutoBattle": null,
          "m_AutoQuickFormation": null,
          "m_QuickTeam": "1",
          "m_ReplayLevel": null,
          "m_ReferOtherTeam": null,
          "m_FullTeam": null,
          "m_CheckIfFails": "1"
        },
        "3": {
          "m_bError": null,
          "m_MainID": "13",
          "m_BattleModeID": "3",
          "m_FirstInherit": "[]",
          "m_BattleGroup": "[]",
          "m_BattleGroupInherit": null,
          "m_CheckErrorRangePercent": "10",
          "m_MonsterType": "[]",
          "m_BPUI": "1",
          "m_AutoBattle": null,
          "m_AutoQuickFormation": null,
          "m_QuickTeam": "1",
          "m_ReplayLevel": null,
          "m_ReferOtherTeam": null,
          "m_FullTeam": null,
          "m_CheckIfFails": "1"
        },
        "4": {
          "m_bError": null,
          "m_MainID": "13",
          "m_BattleModeID": "4",
          "m_FirstInherit": "[]",
          "m_BattleGroup": "[]",
          "m_BattleGroupInherit": null,
          "m_CheckErrorRangePercent": "10",
          "m_MonsterType": "[]",
          "m_BPUI": null,
          "m_AutoBattle": null,
          "m_AutoQuickFormation": null,
          "m_QuickTeam": "1",
          "m_ReplayLevel": null,
          "m_ReferOtherTeam": null,
          "m_FullTeam": null,
          "m_CheckIfFails": "1"
        },
        "5": {
          "m_bError": null,
          "m_MainID": "13",
          "m_BattleModeID": "5",
          "m_FirstInherit": "[]",
          "m_BattleGroup": "[]",
          "m_BattleGroupInherit": null,
          "m_CheckErrorRangePercent": "10",
          "m_MonsterType": "[]",
          "m_BPUI": null,
          "m_AutoBattle": null,
          "m_AutoQuickFormation": null,
          "m_QuickTeam": "1",
          "m_ReplayLevel": null,
          "m_ReferOtherTeam": null,
          "m_FullTeam": null,
          "m_CheckIfFails": "1"
        }
      }
    },
    "14": {
      "_type": "nested_dictionary",
      "_count": 1,
      "_processed": 1,
      "data": {
        "1": {
          "m_bError": null,
          "m_MainID": "14",
          "m_BattleModeID": "1",
          "m_FirstInherit": "[1,1]",
          "m_BattleGroup": "[]",
          "m_BattleGroupInherit": null,
          "m_CheckErrorRangePercent": "10",
          "m_MonsterType": "[]",
          "m_BPUI": null,
          "m_AutoBattle": null,
          "m_AutoQuickFormation": null,
          "m_QuickTeam": "1",
          "m_ReplayLevel": null,
          "m_ReferOtherTeam": null,
          "m_FullTeam": null,
          "m_CheckIfFails": "1"
        }
      }
    }
  },
  "status": "processed_14_items"
}