{
  "className": "CData_ReplaceArenaRank",
  "timestamp": "2025-07-08T13:35:47.099Z",
  "data": {
    "1": {
      "m_bError": null,
      "m_ID": "1",
      "m_RankMin": "1",
      "m_RankMax": "1",
      "m_MatchRankID": "1",
      "m_New": null,
      "m_mName": "\"Bloodlust Slayer 1\"",
      "m_RankIcon": "\"Atlas_Arena/Rank_Godlike\"",
      "m_PVPAFKReward": "[[1058,1666],[1059,1194]]"
    },
    "2": {
      "m_bError": null,
      "m_ID": "2",
      "m_RankMin": "2",
      "m_RankMax": "2",
      "m_MatchRankID": "1",
      "m_New": null,
      "m_mName": "\"Bloodlust Slayer 2\"",
      "m_RankIcon": "\"Atlas_Arena/Rank_Godlike\"",
      "m_PVPAFKReward": "[[1058,1652],[1059,1191]]"
    },
    "3": {
      "m_bError": null,
      "m_ID": "3",
      "m_RankMin": "3",
      "m_RankMax": "3",
      "m_MatchRankID": "1",
      "m_New": null,
      "m_mName": "\"Bloodlust Slayer 3\"",
      "m_RankIcon": "\"Atlas_Arena/Rank_Godlike\"",
      "m_PVPAFKReward": "[[1058,1638],[1059,1188]]"
    },
    "4": {
      "m_bError": null,
      "m_ID": "4",
      "m_RankMin": "4",
      "m_RankMax": "4",
      "m_MatchRankID": "1",
      "m_New": null,
      "m_mName": "\"Bloodlust Slayer 4\"",
      "m_RankIcon": "\"Atlas_Arena/Rank_Godlike\"",
      "m_PVPAFKReward": "[[1058,1625],[1059,1186]]"
    },
    "5": {
      "m_bError": null,
      "m_ID": "5",
      "m_RankMin": "5",
      "m_RankMax": "5",
      "m_MatchRankID": "1",
      "m_New": null,
      "m_mName": "\"Bloodlust Slayer 5\"",
      "m_RankIcon": "\"Atlas_Arena/Rank_Godlike\"",
      "m_PVPAFKReward": "[[1058,1611],[1059,1183]]"
    },
    "6": {
      "m_bError": null,
      "m_ID": "6",
      "m_RankMin": "6",
      "m_RankMax": "6",
      "m_MatchRankID": "1",
      "m_New": null,
      "m_mName": "\"Bloodlust Slayer 6\"",
      "m_RankIcon": "\"Atlas_Arena/Rank_Godlike\"",
      "m_PVPAFKReward": "[[1058,1597],[1059,1180]]"
    },
    "7": {
      "m_bError": null,
      "m_ID": "7",
      "m_RankMin": "7",
      "m_RankMax": "7",
      "m_MatchRankID": "1",
      "m_New": null,
      "m_mName": "\"Bloodlust Slayer 7\"",
      "m_RankIcon": "\"Atlas_Arena/Rank_Godlike\"",
      "m_PVPAFKReward": "[[1058,1583],[1059,1177]]"
    },
    "8": {
      "m_bError": null,
      "m_ID": "8",
      "m_RankMin": "8",
      "m_RankMax": "8",
      "m_MatchRankID": "1",
      "m_New": null,
      "m_mName": "\"Bloodlust Slayer 8\"",
      "m_RankIcon": "\"Atlas_Arena/Rank_Godlike\"",
      "m_PVPAFKReward": "[[1058,1569],[1059,1175]]"
    },
    "9": {
      "m_bError": null,
      "m_ID": "9",
      "m_RankMin": "9",
      "m_RankMax": "9",
      "m_MatchRankID": "1",
      "m_New": null,
      "m_mName": "\"Bloodlust Slayer 9\"",
      "m_RankIcon": "\"Atlas_Arena/Rank_Godlike\"",
      "m_PVPAFKReward": "[[1058,1555],[1059,1172]]"
    },
    "10": {
      "m_bError": null,
      "m_ID": "10",
      "m_RankMin": "10",
      "m_RankMax": "10",
      "m_MatchRankID": "4",
      "m_New": null,
      "m_mName": "\"Bloodlust Slayer 10\"",
      "m_RankIcon": "\"Atlas_Arena/Rank_Godlike\"",
      "m_PVPAFKReward": "[[1058,1541],[1059,1169]]"
    },
    "11": {
      "m_bError": null,
      "m_ID": "11",
      "m_RankMin": "11",
      "m_RankMax": "15",
      "m_MatchRankID": "7",
      "m_New": null,
      "m_mName": "\"Legendary Gladiator 1\"",
      "m_RankIcon": "\"Atlas_Arena/Rank_Legend\"",
      "m_PVPAFKReward": "[[1058,1458],[1059,1166]]"
    },
    "12": {
      "m_bError": null,
      "m_ID": "12",
      "m_RankMin": "16",
      "m_RankMax": "20",
      "m_MatchRankID": "10",
      "m_New": null,
      "m_mName": "\"Legendary Gladiator 2\"",
      "m_RankIcon": "\"Atlas_Arena/Rank_Legend\"",
      "m_PVPAFKReward": "[[1058,1375],[1059,1161]]"
    },
    "13": {
      "m_bError": null,
      "m_ID": "13",
      "m_RankMin": "21",
      "m_RankMax": "30",
      "m_MatchRankID": "11",
      "m_New": null,
      "m_mName": "\"Legendary Gladiator 3\"",
      "m_RankIcon": "\"Atlas_Arena/Rank_Legend\"",
      "m_PVPAFKReward": "[[1058,1291],[1059,1158]]"
    },
    "14": {
      "m_bError": null,
      "m_ID": "14",
      "m_RankMin": "31",
      "m_RankMax": "40",
      "m_MatchRankID": "12",
      "m_New": null,
      "m_mName": "\"Legendary Gladiator 4\"",
      "m_RankIcon": "\"Atlas_Arena/Rank_Legend\"",
      "m_PVPAFKReward": "[[1058,1208],[1059,1155]]"
    },
    "15": {
      "m_bError": null,
      "m_ID": "15",
      "m_RankMin": "41",
      "m_RankMax": "50",
      "m_MatchRankID": "13",
      "m_New": null,
      "m_mName": "\"Legendary Gladiator 5\"",
      "m_RankIcon": "\"Atlas_Arena/Rank_Legend\"",
      "m_PVPAFKReward": "[[1058,1125],[1059,1152]]"
    },
    "16": {
      "m_bError": null,
      "m_ID": "16",
      "m_RankMin": "51",
      "m_RankMax": "60",
      "m_MatchRankID": "14",
      "m_New": null,
      "m_mName": "\"Legendary Gladiator 6\"",
      "m_RankIcon": "\"Atlas_Arena/Rank_Legend\"",
      "m_PVPAFKReward": "[[1058,1041],[1059,1150]]"
    },
    "17": {
      "m_bError": null,
      "m_ID": "17",
      "m_RankMin": "61",
      "m_RankMax": "70",
      "m_MatchRankID": "15",
      "m_New": null,
      "m_mName": "\"Legendary Gladiator 7\"",
      "m_RankIcon": "\"Atlas_Arena/Rank_Legend\"",
      "m_PVPAFKReward": "[[1058,958],[1059,1147]]"
    },
    "18": {
      "m_bError": null,
      "m_ID": "18",
      "m_RankMin": "71",
      "m_RankMax": "80",
      "m_MatchRankID": "16",
      "m_New": null,
      "m_mName": "\"Legendary Gladiator 8\"",
      "m_RankIcon": "\"Atlas_Arena/Rank_Legend\"",
      "m_PVPAFKReward": "[[1058,875],[1059,1144]]"
    },
    "19": {
      "m_bError": null,
      "m_ID": "19",
      "m_RankMin": "81",
      "m_RankMax": "90",
      "m_MatchRankID": "17",
      "m_New": null,
      "m_mName": "\"Legendary Gladiator 9\"",
      "m_RankIcon": "\"Atlas_Arena/Rank_Legend\"",
      "m_PVPAFKReward": "[[1058,791],[1059,1141]]"
    },
    "20": {
      "m_bError": null,
      "m_ID": "20",
      "m_RankMin": "91",
      "m_RankMax": "100",
      "m_MatchRankID": "18",
      "m_New": null,
      "m_mName": "\"Legendary Gladiator 10\"",
      "m_RankIcon": "\"Atlas_Arena/Rank_Legend\"",
      "m_PVPAFKReward": "[[1058,708],[1059,1138]]"
    },
    "21": {
      "m_bError": null,
      "m_ID": "21",
      "m_RankMin": "101",
      "m_RankMax": "110",
      "m_MatchRankID": "19",
      "m_New": null,
      "m_mName": "\"Bloody Gladiator 1\"",
      "m_RankIcon": "\"Atlas_Arena/Rank_Bloody\"",
      "m_PVPAFKReward": "[[1058,625],[1059,1136]]"
    },
    "22": {
      "m_bError": null,
      "m_ID": "22",
      "m_RankMin": "111",
      "m_RankMax": "120",
      "m_MatchRankID": "20",
      "m_New": null,
      "m_mName": "\"Bloody Gladiator 2\"",
      "m_RankIcon": "\"Atlas_Arena/Rank_Bloody\"",
      "m_PVPAFKReward": "[[1058,569],[1059,1133]]"
    },
    "23": {
      "m_bError": null,
      "m_ID": "23",
      "m_RankMin": "121",
      "m_RankMax": "130",
      "m_MatchRankID": "21",
      "m_New": null,
      "m_mName": "\"Bloody Gladiator 3\"",
      "m_RankIcon": "\"Atlas_Arena/Rank_Bloody\"",
      "m_PVPAFKReward": "[[1058,513],[1059,1130]]"
    },
    "24": {
      "m_bError": null,
      "m_ID": "24",
      "m_RankMin": "131",
      "m_RankMax": "140",
      "m_MatchRankID": "22",
      "m_New": null,
      "m_mName": "\"Berserker 1\"",
      "m_RankIcon": "\"Atlas_Arena/Rank_Berserker\"",
      "m_PVPAFKReward": "[[1058,458],[1059,1127]]"
    },
    "25": {
      "m_bError": null,
      "m_ID": "25",
      "m_RankMin": "141",
      "m_RankMax": "150",
      "m_MatchRankID": "23",
      "m_New": null,
      "m_mName": "\"Berserker 2\"",
      "m_RankIcon": "\"Atlas_Arena/Rank_Berserker\"",
      "m_PVPAFKReward": "[[1058,402],[1059,1122]]"
    },
    "26": {
      "m_bError": null,
      "m_ID": "26",
      "m_RankMin": "151",
      "m_RankMax": "160",
      "m_MatchRankID": "24",
      "m_New": null,
      "m_mName": "\"Berserker 3\"",
      "m_RankIcon": "\"Atlas_Arena/Rank_Berserker\"",
      "m_PVPAFKReward": "[[1058,347],[1059,1119]]"
    },
    "27": {
      "m_bError": null,
      "m_ID": "27",
      "m_RankMin": "161",
      "m_RankMax": "170",
      "m_MatchRankID": "25",
      "m_New": null,
      "m_mName": "\"Lone Wolf 1\"",
      "m_RankIcon": "\"Atlas_Arena/Rank_Warrior\"",
      "m_PVPAFKReward": "[[1058,291],[1059,1116]]"
    },
    "28": {
      "m_bError": null,
      "m_ID": "28",
      "m_RankMin": "171",
      "m_RankMax": "180",
      "m_MatchRankID": "26",
      "m_New": null,
      "m_mName": "\"Lone Wolf 2\"",
      "m_RankIcon": "\"Atlas_Arena/Rank_Warrior\"",
      "m_PVPAFKReward": "[[1058,236],[1059,1113]]"
    },
    "29": {
      "m_bError": null,
      "m_ID": "29",
      "m_RankMin": "181",
      "m_RankMax": "190",
      "m_MatchRankID": "27",
      "m_New": null,
      "m_mName": "\"Lone Wolf 3\"",
      "m_RankIcon": "\"Atlas_Arena/Rank_Warrior\"",
      "m_PVPAFKReward": "[[1058,180],[1059,1111]]"
    },
    "30": {
      "m_bError": null,
      "m_ID": "30",
      "m_RankMin": "191",
      "m_RankMax": "200",
      "m_MatchRankID": "28",
      "m_New": null,
      "m_mName": "\"Freeman 1\"",
      "m_RankIcon": "\"Atlas_Arena/Rank_Freeman\"",
      "m_PVPAFKReward": "[[1058,125],[1059,1108]]"
    },
    "31": {
      "m_bError": null,
      "m_ID": "31",
      "m_RankMin": "201",
      "m_RankMax": null,
      "m_MatchRankID": "29",
      "m_New": null,
      "m_mName": "\"Freeman 2\"",
      "m_RankIcon": "\"Atlas_Arena/Rank_Freeman\"",
      "m_PVPAFKReward": "[[1058,69],[1059,1105]]"
    },
    "32": {
      "m_bError": null,
      "m_ID": "32",
      "m_RankMin": null,
      "m_RankMax": null,
      "m_MatchRankID": "30",
      "m_New": "1",
      "m_mName": "\"Duelist\"",
      "m_RankIcon": "\"Atlas_Arena/Rank_Initial\"",
      "m_PVPAFKReward": "[]"
    }
  },
  "status": "processed_32_items"
}